PyDndEdit/Manual.dnd
PyDndEdit/REFERENCE.dnd
PyDndEdit/__main__.py
PyDndEdit/changelog.dnd
PyDndEdit/dndc_js_api.d.ts
PyDndEdit/dndedit.py
PyDndEdit/jsdoc.dnd
PyDndEdit-1.1.2.dist-info/METADATA
PyDndEdit-1.1.2.dist-info/WHEEL
PyDndEdit-1.1.2.dist-info/top_level.txt
PyDndEdit-1.1.2.dist-info/RECORD
