Metadata-Version: 2.1
Name: PyDndEdit
Version: 1.1.2
Summary: Qt based editor for the dnd file format
Author: David Priver
Author-email: david@davidpriver.com
License: Proprietary
Classifier: Development Status :: 4 - Beta
Classifier: License :: Other/Proprietary License
Classifier: Programming Language :: Python :: 3
Classifier: Programming Language :: Python :: 3 :: Only
Requires-Python: >=3.8, <4
Requires-Dist: PySide6
Requires-Dist: pydndc
